{
    "name_file": "traking_NEUROPULSCrossingSide_Arct_N4",
    "arct": "NEUROPULSCrossingSide_Arct",
    "n_inputs": 4,
    "n_epochs": 20000,
    "date": "20240723",
    "train_type": "1-Fidelity",
    "seed": 37,
    "n_matrices": 1000,
    "n_repetitions": 5,
    "lr": 0.001,
    "n_bachup": 500,
    "data_out_type": "Fidelity",
    "rep_type": "max",
    "simulations": [
        {
            "pc_iloss_mu": 0.0,
            "pc_iloss_sigma": 0.0,
            "i_loss_MMI_mu": -0.25,
            "i_loss_MMI_sigma": 0.1,
            "imbalance_mu": -0.25,
            "imbalance_sigma": 0.15,
            "i_loss_Crossing_mu": -0.25,
            "i_loss_Crossing_sigma": 0.05,
            "cross_talk_mu": -35.0,
            "cross_talk_sigma": 1.0,
            "average": 0.9995815497819385,
            "std_dev": 0.000125649217554653
        },
        {
            "pc_iloss_mu": 0.0,
            "pc_iloss_sigma": 0.0,
            "i_loss_MMI_mu": -0.25,
            "i_loss_MMI_sigma": 0.1,
            "imbalance_mu": 0.0,
            "imbalance_sigma": 0.15,
            "i_loss_Crossing_mu": -0.25,
            "i_loss_Crossing_sigma": 0.05,
            "cross_talk_mu": -35.0,
            "cross_talk_sigma": 1.0,
            "average": 0.9995821508780982,
            "std_dev": 0.00012361980971748677
        },
        {
            "pc_iloss_mu": 0.0,
            "pc_iloss_sigma": 0.0,
            "i_loss_MMI_mu": -0.25,
            "i_loss_MMI_sigma": 0.1,
            "imbalance_mu": 0.25,
            "imbalance_sigma": 0.15,
            "i_loss_Crossing_mu": -0.25,
            "i_loss_Crossing_sigma": 0.05,
            "cross_talk_mu": -35.0,
            "cross_talk_sigma": 1.0,
            "average": 0.9995822471081823,
            "std_dev": 0.0001231629899684362
        },
        {
            "pc_iloss_mu": -1.0,
            "pc_iloss_sigma": 0.5,
            "i_loss_MMI_mu": -0.25,
            "i_loss_MMI_sigma": 0.1,
            "imbalance_mu": -0.25,
            "imbalance_sigma": 0.15,
            "i_loss_Crossing_mu": -0.25,
            "i_loss_Crossing_sigma": 0.05,
            "cross_talk_mu": -35.0,
            "cross_talk_sigma": 1.0,
            "average": 0.9823037138317307,
            "std_dev": 0.004272258113388828
        },
        {
            "pc_iloss_mu": -1.0,
            "pc_iloss_sigma": 0.5,
            "i_loss_MMI_mu": -0.25,
            "i_loss_MMI_sigma": 0.1,
            "imbalance_mu": 0.0,
            "imbalance_sigma": 0.15,
            "i_loss_Crossing_mu": -0.25,
            "i_loss_Crossing_sigma": 0.05,
            "cross_talk_mu": -35.0,
            "cross_talk_sigma": 1.0,
            "average": 0.9818782402630636,
            "std_dev": 0.004365596738291235
        },
        {
            "pc_iloss_mu": -1.0,
            "pc_iloss_sigma": 0.5,
            "i_loss_MMI_mu": -0.25,
            "i_loss_MMI_sigma": 0.1,
            "imbalance_mu": 0.25,
            "imbalance_sigma": 0.15,
            "i_loss_Crossing_mu": -0.25,
            "i_loss_Crossing_sigma": 0.05,
            "cross_talk_mu": -35.0,
            "cross_talk_sigma": 1.0,
            "average": 0.9814229777238047,
            "std_dev": 0.004506221255137775
        }
    ]
}