{
    "name_file": "traking_ClementsBell_Arct_N8",
    "arct": "ClementsBell_Arct",
    "n_inputs": 8,
    "n_epochs": 22000,
    "date": "20240723",
    "train_type": "1-Fidelity",
    "seed": 37,
    "n_matrices": 1000,
    "n_repetitions": 5,
    "lr": 0.001,
    "n_bachup": 500,
    "data_out_type": "Fidelity",
    "rep_type": "max",
    "simulations": [
        {
            "PC_i_loss_const": -2.0,
            "i_loss_const": -0.5,
            "imbalance_const": -0.5,
            "cross_talk_const": -30.0,
            "average": 0.9899138329433049,
            "std_dev": 0.002931436954730076
        },
        {
            "PC_i_loss_const": -2.0,
            "i_loss_const": -0.5,
            "imbalance_const": 0.5,
            "cross_talk_const": -30.0,
            "average": 0.9899138440287554,
            "std_dev": 0.0029314274414527944
        },
        {
            "PC_i_loss_const": -2.0,
            "i_loss_const": 0.0,
            "imbalance_const": 0.0,
            "cross_talk_const": -1000.0,
            "average": 0.9999999123057348,
            "std_dev": 7.194918810806192e-07
        },
        {
            "PC_i_loss_const": -1.75,
            "i_loss_const": -0.5,
            "imbalance_const": -0.5,
            "cross_talk_const": -30.0,
            "average": 0.9899138321802621,
            "std_dev": 0.002931437111967569
        },
        {
            "PC_i_loss_const": -1.75,
            "i_loss_const": -0.5,
            "imbalance_const": 0.5,
            "cross_talk_const": -30.0,
            "average": 0.9899138449417487,
            "std_dev": 0.0029314261905817865
        },
        {
            "PC_i_loss_const": -1.75,
            "i_loss_const": 0.0,
            "imbalance_const": 0.0,
            "cross_talk_const": -1000.0,
            "average": 0.9999999126605341,
            "std_dev": 7.189872409658675e-07
        },
        {
            "PC_i_loss_const": -1.5,
            "i_loss_const": -0.5,
            "imbalance_const": -0.5,
            "cross_talk_const": -30.0,
            "average": 0.9899138309108547,
            "std_dev": 0.002931437820237188
        },
        {
            "PC_i_loss_const": -1.5,
            "i_loss_const": -0.5,
            "imbalance_const": 0.5,
            "cross_talk_const": -30.0,
            "average": 0.9899138458669999,
            "std_dev": 0.0029314247804199125
        },
        {
            "PC_i_loss_const": -1.5,
            "i_loss_const": 0.0,
            "imbalance_const": 0.0,
            "cross_talk_const": -1000.0,
            "average": 0.9999999134263774,
            "std_dev": 7.30103747639935e-07
        },
        {
            "PC_i_loss_const": -1.25,
            "i_loss_const": -0.5,
            "imbalance_const": -0.5,
            "cross_talk_const": -30.0,
            "average": 0.9899138342260309,
            "std_dev": 0.0029314361797097882
        },
        {
            "PC_i_loss_const": -1.25,
            "i_loss_const": -0.5,
            "imbalance_const": 0.5,
            "cross_talk_const": -30.0,
            "average": 0.9899138432556748,
            "std_dev": 0.002931427788334225
        },
        {
            "PC_i_loss_const": -1.25,
            "i_loss_const": 0.0,
            "imbalance_const": 0.0,
            "cross_talk_const": -1000.0,
            "average": 0.9999999120769066,
            "std_dev": 7.198202812243156e-07
        },
        {
            "PC_i_loss_const": -1.0,
            "i_loss_const": -0.5,
            "imbalance_const": -0.5,
            "cross_talk_const": -30.0,
            "average": 0.9899138281644527,
            "std_dev": 0.0029314388206098264
        },
        {
            "PC_i_loss_const": -1.0,
            "i_loss_const": -0.5,
            "imbalance_const": 0.5,
            "cross_talk_const": -30.0,
            "average": 0.9899138448334325,
            "std_dev": 0.002931424939311156
        },
        {
            "PC_i_loss_const": -1.0,
            "i_loss_const": 0.0,
            "imbalance_const": 0.0,
            "cross_talk_const": -1000.0,
            "average": 0.9999999091738009,
            "std_dev": 7.276597168710041e-07
        },
        {
            "PC_i_loss_const": -0.75,
            "i_loss_const": -0.5,
            "imbalance_const": -0.5,
            "cross_talk_const": -30.0,
            "average": 0.9899138337455818,
            "std_dev": 0.0029314373800899975
        },
        {
            "PC_i_loss_const": -0.75,
            "i_loss_const": -0.5,
            "imbalance_const": 0.5,
            "cross_talk_const": -30.0,
            "average": 0.98991384376734,
            "std_dev": 0.002931425271472753
        },
        {
            "PC_i_loss_const": -0.75,
            "i_loss_const": 0.0,
            "imbalance_const": 0.0,
            "cross_talk_const": -1000.0,
            "average": 0.9999999132403404,
            "std_dev": 7.20821262513373e-07
        },
        {
            "PC_i_loss_const": -0.5,
            "i_loss_const": -0.5,
            "imbalance_const": -0.5,
            "cross_talk_const": -30.0,
            "average": 0.9899138318368528,
            "std_dev": 0.002931438908969225
        },
        {
            "PC_i_loss_const": -0.5,
            "i_loss_const": -0.5,
            "imbalance_const": 0.5,
            "cross_talk_const": -30.0,
            "average": 0.989913843646942,
            "std_dev": 0.0029314270036997474
        },
        {
            "PC_i_loss_const": -0.5,
            "i_loss_const": 0.0,
            "imbalance_const": 0.0,
            "cross_talk_const": -1000.0,
            "average": 0.9999999112907797,
            "std_dev": 7.223487447939789e-07
        },
        {
            "PC_i_loss_const": -0.25,
            "i_loss_const": -0.5,
            "imbalance_const": -0.5,
            "cross_talk_const": -30.0,
            "average": 0.9899138317121433,
            "std_dev": 0.002931436395930822
        },
        {
            "PC_i_loss_const": -0.25,
            "i_loss_const": -0.5,
            "imbalance_const": 0.5,
            "cross_talk_const": -30.0,
            "average": 0.9899138441702139,
            "std_dev": 0.0029314238925859607
        },
        {
            "PC_i_loss_const": -0.25,
            "i_loss_const": 0.0,
            "imbalance_const": 0.0,
            "cross_talk_const": -1000.0,
            "average": 0.9999999114704483,
            "std_dev": 7.22856743130278e-07
        },
        {
            "PC_i_loss_const": 0.0,
            "i_loss_const": -0.5,
            "imbalance_const": -0.5,
            "cross_talk_const": -30.0,
            "average": 0.9899138325603879,
            "std_dev": 0.0029314345532373788
        },
        {
            "PC_i_loss_const": 0.0,
            "i_loss_const": -0.5,
            "imbalance_const": 0.5,
            "cross_talk_const": -30.0,
            "average": 0.9899138442633305,
            "std_dev": 0.0029314245560699247
        },
        {
            "PC_i_loss_const": 0.0,
            "i_loss_const": 0.0,
            "imbalance_const": 0.0,
            "cross_talk_const": -1000.0,
            "average": 0.9999999123609516,
            "std_dev": 7.207034619556206e-07
        }
    ]
}